flee/Diagnostics.py
flee/InputGeography.py
flee/SimulationSettings.py
flee/__init__.py
flee/_version.py
flee/coupling.py
flee/flee.py
flee/micro_InputGeography.py
flee/moving.py
flee/pflee.py
flee/pmicro_flee.py
flee/scoring.py
flee/spawning.py
flee/datamanager/DataTable.py
flee/datamanager/__init__.py
flee/datamanager/calc_date_difference.py
flee/datamanager/handle_refugee_data.py
flee/datamanager/read_period.py
flee/postprocessing/CalculateDiagnostics.py
flee/postprocessing/FormatPyplotFigures.py
flee/postprocessing/PlotRedirectionComparison.py
flee/postprocessing/StoreDiagnostics.py
flee/postprocessing/__init__.py
flee/postprocessing/_version.py
flee/postprocessing/analysis.py
flee/postprocessing/analyze_graph.py
flee/postprocessing/compare_out.py
flee/postprocessing/extract-validation-results.py
flee/postprocessing/plot-flee-uq-output-more.py
flee/postprocessing/plot_flee_compare.py
flee/postprocessing/plot_flee_forecast.py
flee/postprocessing/plot_flee_output.py
flee/postprocessing/plot_flee_uq_output.py
flee/postprocessing/plotly_flee_output.py
flee/postprocessing/plotter.py
flee-3.1.dist-info/LICENSE
flee-3.1.dist-info/METADATA
flee-3.1.dist-info/WHEEL
flee-3.1.dist-info/top_level.txt
flee-3.1.dist-info/RECORD
