Metadata-Version: 2.1
Name: flee
Version: 3.1
Summary: Flee is an agent-based modelling toolkit which is purpose-built for simulating the movement of individuals across geographical locations.
Home-page: https://flee.readthedocs.io
Author: Derek Groen
Author-email: Derek.Groen@brunel.ac.uk
License: BSD-3-Clause
Keywords: flee
Classifier: Development Status :: 5 - Production/Stable
Classifier: Intended Audience :: Science/Research
Classifier: License :: OSI Approved :: BSD License
Classifier: Operating System :: OS Independent
Classifier: Programming Language :: Python :: 3
Classifier: Programming Language :: Python :: 3.8
Classifier: Programming Language :: Python :: 3.9
Classifier: Programming Language :: Python :: 3.10
Requires-Python: >=3.8
License-File: LICENSE
Requires-Dist: networkx
Requires-Dist: matplotlib
Requires-Dist: pandas
Requires-Dist: pytest
Requires-Dist: mpi4py
Requires-Dist: numpy
Requires-Dist: beartype
Requires-Dist: seaborn
Requires-Dist: muscle3
Requires-Dist: pyyaml
